nirn_proxy/__init__.py
nirn_proxy/bucket_path.py
nirn_proxy/cli.py
nirn_proxy/config.py
nirn_proxy/daemon.py
nirn_proxy/discord_client.py
nirn_proxy/distributed_global.py
nirn_proxy/leaky_bucket.py
nirn_proxy/main.py
nirn_proxy/memberlist.py
nirn_proxy/metrics.py
nirn_proxy/profile.py
nirn_proxy/queue_manager.py
nirn_proxy/request_queue.py
nirn_proxy/util.py
nirn_py-1.0.3.dist-info/licenses/LICENSE
nirn_py-1.0.3.dist-info/METADATA
nirn_py-1.0.3.dist-info/WHEEL
nirn_py-1.0.3.dist-info/entry_points.txt
nirn_py-1.0.3.dist-info/top_level.txt
nirn_py-1.0.3.dist-info/RECORD
