Metadata-Version: 2.4
Name: nirn.py
Version: 1.0.3
Summary: Highly available, transparent & dynamic HTTP proxy for Discord API rate limiting
Author-email: Lorenzo <lorenzo@lvh.lol>
License-Expression: MIT
Project-URL: Homepage, https://github.com/lorenzo132/nirn.py
Project-URL: Repository, https://github.com/lorenzo132/nirn.py
Classifier: Development Status :: 4 - Beta
Classifier: Intended Audience :: Developers
Classifier: Programming Language :: Python :: 3
Classifier: Programming Language :: Python :: 3.8
Classifier: Programming Language :: Python :: 3.9
Classifier: Programming Language :: Python :: 3.10
Classifier: Programming Language :: Python :: 3.11
Classifier: Programming Language :: Python :: 3.12
Classifier: Programming Language :: Python :: 3.13
Requires-Python: >=3.8
License-File: LICENSE
Requires-Dist: aiohttp>=3.8.0
Requires-Dist: prometheus-client>=0.15.0
Requires-Dist: python-dotenv>=0.19.0
Requires-Dist: cachetools>=5.0.0
Requires-Dist: aiodns>=3.0.0
Provides-Extra: cluster
Requires-Dist: aioconsul>=0.2.0; extra == "cluster"
Provides-Extra: dev
Requires-Dist: pytest>=7.0; extra == "dev"
Requires-Dist: pytest-asyncio>=0.21.0; extra == "dev"
Requires-Dist: black; extra == "dev"
Requires-Dist: flake8; extra == "dev"
Dynamic: license-file
